llm_palm/__init__.py
llm_palm-0.1.dist-info/LICENSE
llm_palm-0.1.dist-info/METADATA
llm_palm-0.1.dist-info/WHEEL
llm_palm-0.1.dist-info/entry_points.txt
llm_palm-0.1.dist-info/top_level.txt
llm_palm-0.1.dist-info/RECORD
