Metadata-Version: 2.1
Name: llm-palm
Version: 0.1
Summary: Plugin for LLM adding support for Google's PaLM 2 model
Home-page: https://github.com/simonw/llm-palm
Author: Simon Willison
License: Apache License, Version 2.0
Project-URL: Issues, https://github.com/simonw/llm-palm/issues
Project-URL: CI, https://github.com/simonw/llm-palm/actions
Project-URL: Changelog, https://github.com/simonw/llm-palm/releases
Classifier: License :: OSI Approved :: Apache Software License
Requires-Python: >=3.9
License-File: LICENSE
Requires-Dist: llm (>=0.5)
Requires-Dist: google-generativeai
Provides-Extra: test
Requires-Dist: pytest ; extra == 'test'
Requires-Dist: pytest-asyncio ; extra == 'test'
